itmpl/__init__.py
itmpl/config.py
itmpl/global_vars.py
itmpl/main.py
itmpl/metadata.py
itmpl/templates/mkdocs-material-site/.itmpl.py
itmpl/templates/mkdocs-material-site/.itmpl.requirements.dev.txt
itmpl/templates/mkdocs-material-site/.itmpl.toml
itmpl/templates/mkdocs-material-site/docs/gen_ref_pages.py
itmpl/templates/mkdocs-material-site/docs/index.md
itmpl/templates/mkdocs-material-site/docs/static/images/favicon.ico
itmpl/templates/mkdocs-material-site/docs/stylesheets/schemes.css
itmpl/templates/mkdocs-material-site/mkdocs.yml
itmpl/templates/poetry-project/.gitignore
itmpl/templates/poetry-project/.itmpl.py
itmpl/templates/poetry-project/.itmpl.requirements.dev.txt
itmpl/templates/poetry-project/.itmpl.toml
itmpl/templates/poetry-project/.pre-commit-config.yaml
itmpl/templates/poetry-project/README.md
itmpl/templates/poetry-project/pyproject.toml
itmpl/templates/poetry-project/tests/__init__.py
itmpl/templates/poetry-project/tests/test_passing.py
itmpl/templates/poetry-project/tox.ini
itmpl/templates/poetry-project/{{ project_name }}/__init__.py
itmpl/templating.py
itmpl/tree_utils.py
itmpl/utils.py
itmpl-0.1.9.dist-info/LICENSE
itmpl-0.1.9.dist-info/METADATA
itmpl-0.1.9.dist-info/WHEEL
itmpl-0.1.9.dist-info/entry_points.txt
itmpl-0.1.9.dist-info/RECORD
