Metadata-Version: 2.1
Name: itmpl
Version: 0.1.9
Summary: A project templating and scaffolding tool
Home-page: https://itmpl.ihh.dev
License: GPL-3.0-or-later
Author: Isaac Harris-Holt
Author-email: isaac@harris-holt.com
Requires-Python: >=3.8,<4.0
Classifier: License :: OSI Approved :: GNU General Public License v3 or later (GPLv3+)
Classifier: Programming Language :: Python :: 3
Classifier: Programming Language :: Python :: 3.8
Classifier: Programming Language :: Python :: 3.9
Classifier: Programming Language :: Python :: 3.10
Classifier: Programming Language :: Python :: 3.11
Requires-Dist: jinja2 (>=3.1.2,<4.0.0)
Requires-Dist: pydantic (>=1.10.4,<2.0.0)
Requires-Dist: rich (>=13.3.1,<14.0.0)
Requires-Dist: tomli (>=2.0.1,<3.0.0)
Requires-Dist: typer (>=0.7.0,<0.8.0)
Project-URL: Documentation, https://itmpl.ihh.dev
Project-URL: Repository, https://github.com/isaacharrisholt/itmpl
